aliyunsdkimagerecog/__init__.py
aliyunsdkimagerecog/endpoint.py
aliyunsdkimagerecog/request/__init__.py
aliyunsdkimagerecog/request/v20190930/ClassifyingRubbishRequest.py
aliyunsdkimagerecog/request/v20190930/DetectFruitsRequest.py
aliyunsdkimagerecog/request/v20190930/DetectImageElementsRequest.py
aliyunsdkimagerecog/request/v20190930/EvaluateCertificateQualityRequest.py
aliyunsdkimagerecog/request/v20190930/GetAsyncJobResultRequest.py
aliyunsdkimagerecog/request/v20190930/RecognizeFoodRequest.py
aliyunsdkimagerecog/request/v20190930/RecognizeImageColorRequest.py
aliyunsdkimagerecog/request/v20190930/RecognizeImageStyleRequest.py
aliyunsdkimagerecog/request/v20190930/RecognizeSceneRequest.py
aliyunsdkimagerecog/request/v20190930/RecognizeVehicleTypeRequest.py
aliyunsdkimagerecog/request/v20190930/TaggingAdImageRequest.py
aliyunsdkimagerecog/request/v20190930/TaggingImageRequest.py
aliyunsdkimagerecog/request/v20190930/__init__.py
aliyun_python_sdk_imagerecog-1.0.19.dist-info/LICENSE
aliyun_python_sdk_imagerecog-1.0.19.dist-info/METADATA
aliyun_python_sdk_imagerecog-1.0.19.dist-info/WHEEL
aliyun_python_sdk_imagerecog-1.0.19.dist-info/top_level.txt
aliyun_python_sdk_imagerecog-1.0.19.dist-info/RECORD
